{
	"data": [
		{
			"id": 1,
			"name": "NC News API- Backend",
			"createdAt": "2024-04-13T04:18:19Z",
			"url": "https://github.com/WanwanShi/back_end_project-NC_news",
			"description": "A RESTful API that provides news articles and comments and built with Node.js, Express.js, and PostgreSQL. It also includes tests using Jest.",
			"isFork": false,
			"languages": [
				{
					"name": "JavaScript",
					"iconifyClass": "javascript.png"
				},
				{
					"name": "Express.Js",
					"iconifyClass": "expressjs.png"
				},
				{
					"name": "PostgreSQL",
					"iconifyClass": "postgresql.png"
				},
				{
					"name": "Jest",
					"iconifyClass": "jest.png"
				},
				{
					"name": "Node.js",
					"iconifyClass": "nodejs.png"
				}
			]
		},
		{
			"id": 2,
			"name": "NC News Web",
			"createdAt": "2024-05-13T20:41:33Z",
			"url": "https://nc-news-ws.netlify.app/",
			"description": "📰 A web app that allows users to browse news articles and comments on different topics, and to create their own comments and ratings.",
			"isFork": false,
			"languages": [
				{
					"name": "HTML",
					"iconifyClass": "html5.png"
				},
				{
					"name": "CSS",
					"iconifyClass": "css3.png"
				},
				{
					"name": "JavaScript",
					"iconifyClass": "javascript.png"
				},
				{
					"name": "React",
					"iconifyClass": "react.png"
				},
				{
					"name": "Tailwind CSS",
					"iconifyClass": "tailwindcss.png"
				},
				{
					"name": "MUI",
					"iconifyClass": "mui.png"
				}
			]
		},
		{
			"id": 3,
			"name": "SkillFlash",
			"createdAt": "2024-05-20T14:50:20Z",
			"url": "https://www.youtube.com/watch?v=SO_99qK_RqM",
			"description": "🔥 An AI powered cross-platform mobile app that helps users to prepare for the tech interview by creating review flashcards tailored to specific tech jobs.",
			"isFork": false,
			"languages": [
				{
					"name": "React-Native",
					"iconifyClass": "react-native.png"
				},
				{
					"name": "CSS",
					"iconifyClass": "css3.png"
				},
				{
					"name": "MongoDB",
					"iconifyClass": "mongodb.png"
				},
				{
					"name": "TypeScript",
					"iconifyClass": "typescript.png"
				},
				{
					"name": "Express.Js",
					"iconifyClass": "expressjs.png"
				},
				{
					"name": "Node.js",
					"iconifyClass": "nodejs.png"
				}
			]
		},
		{
			"id": 4,
			"name": "Portfolio Website",
			"createdAt": "2024-6-20 T17:56:07Z",
			"url": "https://github.com/WanwanShi/Wanwanshi",
			"description": "👩🏻‍💻 Responsive portfolio website with projects skills and experience section.",
			"isFork": false,
			"languages": [
				{
					"name": "HTML",
					"iconifyClass": "html5.png"
				},
				{
					"name": "CSS",
					"iconifyClass": "css3.png"
				},
				{
					"name": "JavaScript",
					"iconifyClass": "javascript.png"
				},
				{
					"name": "React",
					"iconifyClass": "react.png"
				},
				{
					"name": "Bootstrap",
					"iconifyClass": "bootstrap.png"
				},
				{
					"name": "MUI",
					"iconifyClass": "mui.png"
				}
			]
		},
		{
			"id": 5,
			"name": "Maths Solver App (In Progress)",
			"createdAt": "2024-6-23 T17:56:07Z",
			"url": "",
			"description": "🧮 I am currently developing a handwriting recognition app that interprets and solves math calculations, plots graphs, and performs calculus operations. The app aims to enhance learning by recognizing handwritten mathematical expressions and converting them into digital format for seamless processing and real-time graph plotting.",
			"isFork": false,
			"languages": [
				{
					"name": "HTML",
					"iconifyClass": "html5.png"
				},
				{
					"name": "CSS",
					"iconifyClass": "css3.png"
				},
				{
					"name": "TypeScript",
					"iconifyClass": "typescript.png"
				},
				{
					"name": "React-Native",
					"iconifyClass": "react-native.png"
				},
				{
					"name": "Bootstrap",
					"iconifyClass": "bootstrap.png"
				},
				{
					"name": "MUI",
					"iconifyClass": "mui.png"
				},
				{
					"name": "Firebase",
					"iconifyClass": "firebase.png"
				}
			]
		}
	]
}
